magscope/__init__.py
magscope/_logging.py
magscope/beadlock.py
magscope/camera.py
magscope/datatypes.py
magscope/default_settings.yaml
magscope/hardware.py
magscope/ipc.py
magscope/ipc_commands.py
magscope/main_dev.py
magscope/processes.py
magscope/scope.py
magscope/scripting.py
magscope/simulation_zlut.txt
magscope/utils.py
magscope/videoprocessing.py
magscope/gui/__init__.py
magscope/gui/controls.py
magscope/gui/panel_layout.py
magscope/gui/plots.py
magscope/gui/video_viewer.py
magscope/gui/widgets.py
magscope/gui/windows.py
magscope-0.2.1.dist-info/licenses/license
magscope-0.2.1.dist-info/METADATA
magscope-0.2.1.dist-info/WHEEL
magscope-0.2.1.dist-info/top_level.txt
magscope-0.2.1.dist-info/RECORD
