Metadata-Version: 2.4
Name: magscope
Version: 0.2.1
Summary: Python framework for live data acquisition and analysis in magnetic tweezers microscopy
Author-email: James London <7jameslondon@gmail.com>
License-Expression: GPL-3.0
Project-URL: Homepage, https://github.com/7jameslondon/MagScope
Project-URL: Source, https://github.com/7jameslondon/MagScope
Project-URL: Documentation, https://magscope.readthedocs.io
Project-URL: Issues, https://github.com/7jameslondon/MagScope/issues
Classifier: Programming Language :: Python :: 3.11
Classifier: Programming Language :: Python :: 3.12
Classifier: Programming Language :: Python :: 3.13
Classifier: Operating System :: Microsoft :: Windows
Classifier: Operating System :: MacOS
Classifier: Operating System :: POSIX :: Linux
Classifier: Intended Audience :: Science/Research
Classifier: Topic :: Scientific/Engineering :: Image Processing
Requires-Python: >=3.11
License-File: license
Requires-Dist: numpy>=1.26
Requires-Dist: scipy>=1.11.1
Requires-Dist: matplotlib
Requires-Dist: tifffile
Requires-Dist: PyYAML
Requires-Dist: magtrack>=0.7
Requires-Dist: PyQt6
Provides-Extra: cpu
Provides-Extra: cu11
Requires-Dist: cupy-cuda11x>=12.0; extra == "cu11"
Provides-Extra: cu12
Requires-Dist: cupy-cuda12x>=13.0; extra == "cu12"
Provides-Extra: cu13
Requires-Dist: cupy-cuda13x>=13.0; extra == "cu13"
Provides-Extra: test
Requires-Dist: pytest; extra == "test"
Provides-Extra: docs
Requires-Dist: sphinx>=7; extra == "docs"
Requires-Dist: furo; extra == "docs"
Requires-Dist: myst-parser; extra == "docs"
Requires-Dist: sphinx-autoapi; extra == "docs"
Requires-Dist: sphinx-copybutton; extra == "docs"
Requires-Dist: sphinx-design; extra == "docs"
Requires-Dist: sphinx-autodoc-typehints; extra == "docs"
Requires-Dist: sphinx-book-theme; extra == "docs"
Dynamic: license-file
